lil_aretomo/__init__.py
lil_aretomo/_version.py
lil_aretomo/aretomo.py
lil_aretomo/output.py
lil_aretomo/utils.py
lil_aretomo-0.1.1.dist-info/LICENSE
lil_aretomo-0.1.1.dist-info/METADATA
lil_aretomo-0.1.1.dist-info/WHEEL
lil_aretomo-0.1.1.dist-info/top_level.txt
lil_aretomo-0.1.1.dist-info/RECORD
