Metadata-Version: 2.1
Name: lil_aretomo
Version: 0.1.1
Summary: AreTomo (w)rapper for rln4
Home-page: https://github.com/EuanPyle/lil_aretomo
Author: Euan Pyle
Author-email: euanpyle@gmail.com
License: BSD-3-Clause
Project-URL: Source Code, https://github.com/EuanPyle/lil_aretomo
Classifier: Development Status :: 2 - Pre-Alpha
Classifier: License :: OSI Approved :: BSD License
Classifier: Natural Language :: English
Classifier: Programming Language :: Python :: 3
Classifier: Programming Language :: Python :: 3 :: Only
Classifier: Programming Language :: Python :: 3.8
Classifier: Programming Language :: Python :: 3.9
Classifier: Programming Language :: Python :: 3.10
Requires-Python: >=3.8
License-File: LICENSE
Requires-Dist: numpy
Requires-Dist: pandas
Requires-Dist: mrcfile >=1.4.0
Requires-Dist: typer
Requires-Dist: rich
Provides-Extra: dev
Requires-Dist: black ; extra == 'dev'
Requires-Dist: flake8 ; extra == 'dev'
Requires-Dist: flake8-docstrings ; extra == 'dev'
Requires-Dist: ipython ; extra == 'dev'
Requires-Dist: isort ; extra == 'dev'
Requires-Dist: jedi <0.18.0 ; extra == 'dev'
Requires-Dist: mypy ; extra == 'dev'
Requires-Dist: pre-commit ; extra == 'dev'
Requires-Dist: pydocstyle ; extra == 'dev'
Requires-Dist: pytest ; extra == 'dev'
Provides-Extra: testing
Requires-Dist: pytest ; extra == 'testing'
